py_af_colours/__init__.py
py_af_colours/py_af_colours.py
py_af_colours/config/config.yaml
tests/__init__.py
tests/test_categorical_duo_output.py
tests/test_list_length.py
tests/test_value_errors.py
py_af_colours-1.0.6.dist-info/LICENSE
py_af_colours-1.0.6.dist-info/METADATA
py_af_colours-1.0.6.dist-info/WHEEL
py_af_colours-1.0.6.dist-info/top_level.txt
py_af_colours-1.0.6.dist-info/RECORD
