Metadata-Version: 2.1
Name: py-af-colours
Version: 1.0.6
Summary: UK Government Analysis Function recommended colour palettes for creating accessible graphics
Home-page: https://best-practice-and-impact.github.io/py-af-colours/
Author: Analysis standards and Pipelines team
Author-email: Analysis Standards and Pipelines Team <asap@ons.gov.uk>
License: MIT License
Project-URL: Docs, https://best-practice-and-impact.github.io/py-af-colours/
Classifier: Programming Language :: Python :: 3
Classifier: Operating System :: OS Independent
Requires-Python: >=3.7
License-File: LICENSE
Requires-Dist: PyYAML >=5.0
